Workbook
Name Slicer_Months__Order_date: #N/A
Name Slicer_product: #N/A
Name Slicer_region: #N/A
Name Slicer_salesperson: #N/A

Sheet sales data
A1: Order ID | B1: Order date | C1: salesperson | D1: region | E1: product | F1: category | G1: quantity | H1: unit price | I1: discount | J1: revenue | K1: cost | L1: profit
A2: ORD-1001 | B2: 45662 | C2: Rahul | D2: North | E2: Laptop | F2: =VLOOKUP(E2,'lookup lists'!$F$2:$H$9,2,FALSE) -> Electronics | G2: 2 | H2: 65000 | I2: 0.05 | J2: =G2*H2*(1-I2) -> 123500 | K2: =G2*VLOOKUP(E2,'lookup lists'!$F$2:$H$9,3,FALSE) -> 86000 | L2: =J2-K2 -> 37500
A3: ORD-1002 | B3: 45665 | C3: Priya | D3: South | E3: Chair | F3: Furniture | G3: 5 | H3: 5500 | I3: 0.1 | J3: =G3*H3*(1-I3) -> 24750 | K3: =G3*VLOOKUP(E3,'lookup lists'!$F$2:$H$9,3,FALSE) -> 16500 | L3: =J3-K3 -> 8250
A4: ORD-1003 | B4: 45669 | C4: Amit | D4: East | E4: Notebook | F4: Office Supplies | G4: 20 | H4: 120 | I4: 0 | J4: =G4*H4*(1-I4) -> 2400 | K4: =G4*VLOOKUP(E4,'lookup lists'!$F$2:$H$9,3,FALSE) -> 1400 | L4: =J4-K4 -> 1000
A5: ORD-1004 | B5: 45673 | C5: Neha | D5: West | E5: Monitor | F5: Electronics | G5: 3 | H5: 18000 | I5: 0.05 | J5: =G5*H5*(1-I5) -> 51300 | K5: =G5*VLOOKUP(E5,'lookup lists'!$F$2:$H$9,3,FALSE) -> 36000 | L5: =J5-K5 -> 15300
A6: ORD-1005 | B6: 45678 | C6: Arjun | D6: North | E6: Desk | F6: Furniture | G6: 2 | H6: 14000 | I6: 0.08 | J6: =G6*H6*(1-I6) -> 25760 | K6: =G6*VLOOKUP(E6,'lookup lists'!$F$2:$H$9,3,FALSE) -> 18000 | L6: =J6-K6 -> 7760
A7: ORD-1006 | B7: 45684 | C7: Sneha | D7: South | E7: Printer | F7: Electronics | G7: 2 | H7: 22000 | I7: 0.1 | J7: =G7*H7*(1-I7) -> 39600 | K7: =G7*VLOOKUP(E7,'lookup lists'!$F$2:$H$9,3,FALSE) -> 30000 | L7: =J7-K7 -> 9600
A8: ORD-1007 | B8: 45691 | C8: Rahul | D8: East | E8: Keyboard | F8: Electronics | G8: 8 | H8: 1800 | I8: 0.05 | J8: =G8*H8*(1-I8) -> 13680 | K8: =G8*VLOOKUP(E8,'lookup lists'!$F$2:$H$9,3,FALSE) -> 7200 | L8: =J8-K8 -> 6480
A9: ORD-1008 | B9: 45695 | C9: Priya | D9: West | E9: Pen | F9: Office Supplies | G9: 50 | H9: 35 | I9: 0 | J9: =G9*H9*(1-I9) -> 1750 | K9: =G9*VLOOKUP(E9,'lookup lists'!$F$2:$H$9,3,FALSE) -> 900 | L9: =J9-K9 -> 850
A10: ORD-1009 | B10: 45699 | C10: Amit | D10: North | E10: Monitor | F10: Electronics | G10: 4 | H10: 18000 | I10: 0.08 | J10: =G10*H10*(1-I10) -> 66240 | K10: =G10*VLOOKUP(E10,'lookup lists'!$F$2:$H$9,3,FALSE) -> 48000 | L10: =J10-K10 -> 18240
A11: ORD-1010 | B11: 45703 | C11: Neha | D11: South | E11: Chair | F11: Furniture | G11: 6 | H11: 5500 | I11: 0.05 | J11: =G11*H11*(1-I11) -> 31350 | K11: =G11*VLOOKUP(E11,'lookup lists'!$F$2:$H$9,3,FALSE) -> 19800 | L11: =J11-K11 -> 11550
A12: ORD-1011 | B12: 45707 | C12: Arjun | D12: East | E12: Laptop | F12: Electronics | G12: 1 | H12: 65000 | I12: 0.1 | J12: =G12*H12*(1-I12) -> 58500 | K12: =G12*VLOOKUP(E12,'lookup lists'!$F$2:$H$9,3,FALSE) -> 43000 | L12: =J12-K12 -> 15500
A13: ORD-1012 | B13: 45713 | C13: Sneha | D13: West | E13: Notebook | F13: Office Supplies | G13: 30 | H13: 120 | I13: 0 | J13: =G13*H13*(1-I13) -> 3600 | K13: =G13*VLOOKUP(E13,'lookup lists'!$F$2:$H$9,3,FALSE) -> 2100 | L13: =J13-K13 -> 1500
A14: ORD-1013 | B14: 45718 | C14: Rahul | D14: North | E14: Printer | F14: Electronics | G14: 3 | H14: 22000 | I14: 0.05 | J14: =G14*H14*(1-I14) -> 62700 | K14: =G14*VLOOKUP(E14,'lookup lists'!$F$2:$H$9,3,FALSE) -> 45000 | L14: =J14-K14 -> 17700
... A25: ORD-1024 | B25: 45775 | C25: Sneha | D25: West | E25: Keyboard | F25: Electronics | G25: 12 | H25: 1800 | I25: 0.1 | J25: =G25*H25*(1-I25) -> 19440 | K25: =G25*VLOOKUP(E25,'lookup lists'!$F$2:$H$9,3,FALSE) -> 10800 | L25: =J25-K25 -> 8640

Sheet dashboard
B3: sales performance dashboard
B5: total revenue | E5: total profit | H5: total orders | K5: average order value
B6: =SUM('sales data'!J:J) -> 951390 | E6: =SUM('sales data'!L:L) -> 292250 | H6: =COUNTA('sales data'!A:A)-1 -> 24 | K6: =B6/H6 -> 39641.25

Sheet pivot tables
A1: Sales by region | E1: sales by product
A3: Row Labels | B3: Sum of revenue | E3: Row Labels | F3: Sum of revenue
A4: East | B4: 235880 | E4: Chair | F4: 75900
A5: North | B5: 285800 | E5: Desk | F5: 89600
A6: South | B6: 209220 | E6: Keyboard | F6: 51120
A7: West | B7: 220490 | E7: Laptop | F7: 429000
A8: Grand Total | B8: 951390 | E8: Monitor | F8: 167220
E9: Notebook | F9: 10800
E10: Pen | F10: 4550
E11: Printer | F11: 123200
E12: Grand Total | F12: 951390
A15: sales by salesperson | F15: sales by order date
A17: Row Labels | B17: Sum of revenue | G17: Row Labels | H17: Sum of revenue
A18: Amit | B18: 91440 | G18: Jan | H18: 267310
A19: Arjun | B19: 210560 | G19: Feb | H19: 175120
A20: Neha | B20: 244790 | G20: Mar | H20: 281880
A21: Priya | B21: 72600 | G21: Apr | H21: 227080
A22: Rahul | B22: 219680 | G22: Grand Total | H22: 951390
A23: Sneha | B23: 112320
A24: Grand Total | B24: 951390

Sheet lookup lists
A1: salesperson | B1: regions | C1: category | D1: products | F1: Product | G1: Category | H1: Unit Cost
A2: rahul | B2: north | C2: electronics | D2: laptop | F2: Laptop | G2: Electronics | H2: 43000
A3: priya | B3: south | C3: furniture | D3: monitor | F3: Monitor | G3: Electronics | H3: 12000
A4: amit | B4: east | C4: office supplies | D4: keyboard | F4: Keyboard | G4: Electronics | H4: 900
A5: neha | B5: west | D5: chair | F5: Chair | G5: Furniture | H5: 3300
A6: arjun | D6: desk | F6: Desk | G6: Furniture | H6: 9000
A7: sneha | D7: printer | F7: Printer | G7: Electronics | H7: 15000
D8: notebook | F8: Notebook | G8: Office Supplies | H8: 70
D9: pen | F9: Pen | G9: Office Supplies | H9: 18
